functiongroup/__init__.py
functiongroup/functiongroup.py
functiongroup-0.1.5.dist-info/LICENSE
functiongroup-0.1.5.dist-info/METADATA
functiongroup-0.1.5.dist-info/WHEEL
functiongroup-0.1.5.dist-info/RECORD
