Metadata-Version: 2.1
Name: functiongroup
Version: 0.1.5
Summary: Python utility to implement protocols with pure functions
License: MIT
Keywords: functional,protocol,python
Author: Dennis Rall
Author-email: dennis.rall@web.de
Requires-Python: >=3.11,<4.0
Classifier: License :: OSI Approved :: MIT License
Classifier: Operating System :: OS Independent
Classifier: Programming Language :: Python :: 3
Classifier: Programming Language :: Python :: 3.11
Project-URL: Documentation, https://github.com/dennisrall/functiongroup
Project-URL: Homepage, https://github.com/dennisrall/functiongroup
Project-URL: Repository, https://github.com/dennisrall/functiongroup
